psap/__init__.py
psap/_version.py
psap/classifier.py
psap/cli.py
psap/matrix.py
psap/data/assets/uniprot_ids.txt
psap/data/model/UP000005640_9606_llps.json
psap/data/testing/testset.fasta
psap-1.0.7.dist-info/LICENSE
psap-1.0.7.dist-info/METADATA
psap-1.0.7.dist-info/WHEEL
psap-1.0.7.dist-info/entry_points.txt
psap-1.0.7.dist-info/top_level.txt
psap-1.0.7.dist-info/RECORD
