Metadata-Version: 2.1
Name: psap
Version: 1.0.7
Summary: CLI interface for the PSAP classifier. PSAP implements a RandomForest approach to predict the probability of proteins to mediate protein phase separation (PPS).
Home-page: https://github.com/vanheeringen-lab/psap
Author: ['Juriaan Jansen', 'Tilman Schaefers <tilman.schaefers@ru.nl>']
License: MIT license
Keywords: psap
Platform: UNKNOWN
Classifier: Development Status :: 5 - Production/Stable
Classifier: Intended Audience :: Developers
Classifier: License :: OSI Approved :: MIT License
Classifier: Natural Language :: English
Classifier: Programming Language :: Python :: 3
Classifier: Programming Language :: Python :: 3.5
Classifier: Programming Language :: Python :: 3.6
Classifier: Programming Language :: Python :: 3.7
Classifier: Programming Language :: Python :: 3.8
Requires-Python: >=3.7
License-File: LICENSE
Requires-Dist: pip (>=21.1)
Requires-Dist: wheel (>=0.36.2)
Requires-Dist: scikit-learn (~=0.21)
Requires-Dist: twine (>=1.14.0)
Requires-Dist: pandas (>=1.0.1)
Requires-Dist: biopython (>=1.73)
Requires-Dist: scipy (>=1.2.0)
Requires-Dist: tqdm (>=4.38.0)
Requires-Dist: seaborn (>=0.11.1)
Requires-Dist: matplotlib (>=3.3.4)
Requires-Dist: sklearn-json (>=0.1.0)
Requires-Dist: versioneer (>=0.19)
Requires-Dist: loguru (>=0.5.3)
Requires-Dist: black (>=20.8b1)
